geodist/__init__.py
geodist/geo.py
geodist-0.4.dist-info/LICENSE
geodist-0.4.dist-info/METADATA
geodist-0.4.dist-info/WHEEL
geodist-0.4.dist-info/top_level.txt
geodist-0.4.dist-info/RECORD
