Metadata-Version: 2.1
Name: geodist
Version: 0.4
Summary: GeoDist Package
Home-page: https://github.com/dorhay/geodist
Author: Dor Hay
Author-email: dorhay@gmail.com
License: UNKNOWN
Platform: UNKNOWN
Classifier: Programming Language :: Python :: 3
Classifier: License :: OSI Approved :: BSD License
Classifier: Operating System :: OS Independent
Classifier: Development Status :: 5 - Production/Stable
Classifier: Intended Audience :: Developers
Classifier: Topic :: Software Development :: Build Tools
Requires-Python: >=3.7
Requires-Dist: pyproj
Requires-Dist: shapely
